mapdump/__init__.py
mapdump/__main__.py
mapdump/definitions.py
mapdump/memory.py
mapdump/parser.py
mapdump/symbol.py
mapdump-1.0.1.dist-info/LICENSE
mapdump-1.0.1.dist-info/METADATA
mapdump-1.0.1.dist-info/WHEEL
mapdump-1.0.1.dist-info/entry_points.txt
mapdump-1.0.1.dist-info/top_level.txt
mapdump-1.0.1.dist-info/RECORD
