Metadata-Version: 2.1
Name: mapdump
Version: 1.0.1
Summary: A CLI tool that analyzes the memory usage of a binary via its .map file.
Home-page: https://github.com/sorjente/mapdump
Author: Ayoub Sabri, Dimitri Kokkonis
Author-email: sabriayoub96@gmail.com, kokkonisd@gmail.com
License: UNKNOWN
Platform: UNKNOWN
Classifier: Programming Language :: Python :: 3
Classifier: License :: OSI Approved :: GNU General Public License v3 (GPLv3)
Classifier: Operating System :: OS Independent
Requires-Dist: click
